README.md
__init__.py
cv_sample_add.py
cv_sample_aes.py
cv_sample_sub.py
setup.py
cv_sample_package_03.egg-info/PKG-INFO
cv_sample_package_03.egg-info/SOURCES.txt
cv_sample_package_03.egg-info/dependency_links.txt
cv_sample_package_03.egg-info/requires.txt
cv_sample_package_03.egg-info/top_level.txt